libervia_backend-0.8.0.data/data/share/dbus-1/services/org.libervia.Libervia.service
libervia_backend-0.8.0.data/data/share/doc/libervia-backend/CHANGELOG
libervia_backend-0.8.0.data/data/share/doc/libervia-backend/COPYING
libervia_backend-0.8.0.data/data/share/doc/libervia-backend/INSTALL
libervia_backend-0.8.0.data/data/share/doc/libervia-backend/README
libervia_backend-0.8.0.data/data/share/doc/libervia-backend/README4TRANSLATORS
libervia_backend-0.8.0.data/data/share/locale/fr/LC_MESSAGES/sat.mo
sat/VERSION
sat/__init__.py
sat/bridge/__init__.py
sat/bridge/dbus_bridge.py
sat/bridge/pb.py
sat/bridge/bridge_constructor/__init__.py
sat/bridge/bridge_constructor/base_constructor.py
sat/bridge/bridge_constructor/bridge_constructor.py
sat/bridge/bridge_constructor/constants.py
sat/bridge/bridge_constructor/constructors/__init__.py
sat/bridge/bridge_constructor/constructors/dbus/__init__.py
sat/bridge/bridge_constructor/constructors/dbus/constructor.py
sat/bridge/bridge_constructor/constructors/dbus/dbus_core_template.py
sat/bridge/bridge_constructor/constructors/dbus/dbus_frontend_template.py
sat/bridge/bridge_constructor/constructors/dbus-xml/__init__.py
sat/bridge/bridge_constructor/constructors/dbus-xml/constructor.py
sat/bridge/bridge_constructor/constructors/embedded/__init__.py
sat/bridge/bridge_constructor/constructors/embedded/constructor.py
sat/bridge/bridge_constructor/constructors/embedded/embedded_frontend_template.py
sat/bridge/bridge_constructor/constructors/embedded/embedded_template.py
sat/bridge/bridge_constructor/constructors/mediawiki/__init__.py
sat/bridge/bridge_constructor/constructors/mediawiki/constructor.py
sat/bridge/bridge_constructor/constructors/pb/__init__.py
sat/bridge/bridge_constructor/constructors/pb/constructor.py
sat/bridge/bridge_constructor/constructors/pb/pb_core_template.py
sat/bridge/bridge_constructor/constructors/pb/pb_frontend_template.py
sat/core/__init__.py
sat/core/constants.py
sat/core/exceptions.py
sat/core/i18n.py
libervia_backend-0.8.0.dist-info/COPYING
libervia_backend-0.8.0.dist-info/METADATA
libervia_backend-0.8.0.dist-info/WHEEL
libervia_backend-0.8.0.dist-info/entry_points.txt
libervia_backend-0.8.0.dist-info/top_level.txt
libervia_backend-0.8.0.dist-info/RECORD
