Metadata-Version: 2.1
Name: libervia-backend
Version: 0.8.0
Summary: Libervia multipurpose and multi frontend XMPP client
Home-page: https://salut-a-toi.org
Author: Association « Salut à Toi »
Author-email: contact@goffi.org
License: UNKNOWN
Platform: UNKNOWN
Classifier: Programming Language :: Python :: 3 :: Only
Classifier: Programming Language :: Python :: 3.7
Classifier: Programming Language :: Python :: 3.8
Classifier: Programming Language :: Python :: 3.9
Classifier: Development Status :: 5 - Production/Stable
Classifier: Environment :: Console
Classifier: Framework :: Twisted
Classifier: License :: OSI Approved :: GNU Affero General Public License v3 or later (AGPLv3+)
Classifier: Operating System :: POSIX :: Linux
Classifier: Topic :: Communications :: Chat
Requires-Python: >=3.7
License-File: COPYING
Requires-Dist: babel (<3)
Requires-Dist: dbus-python (<1.3)
Requires-Dist: html2text (<2020.2)
Requires-Dist: jinja2 (>=2.10.3)
Requires-Dist: langid (<2)
Requires-Dist: lxml (>=3.1.0)
Requires-Dist: markdown (>=3.0)
Requires-Dist: miniupnpc (<2.1)
Requires-Dist: mutagen (<2)
Requires-Dist: netifaces (<0.12)
Requires-Dist: pillow (>=6.0.0)
Requires-Dist: progressbar2 (<3.54)
Requires-Dist: cryptography (<3.5)
Requires-Dist: pygments (<3)
Requires-Dist: pygobject (<3.40.1)
Requires-Dist: pyopenssl (<21.0.0)
Requires-Dist: python-dateutil (<3,>=2.8.1)
Requires-Dist: python-potr (<1.1)
Requires-Dist: pyxdg (<0.30)
Requires-Dist: sat-tmp (<0.9,>=0.8.0b1)
Requires-Dist: shortuuid (<1.1)
Requires-Dist: twisted[tls] (<21.3.0,>=20.3.0)
Requires-Dist: treq (<22.0.0)
Requires-Dist: urwid (<3,>=1.2.0)
Requires-Dist: urwid-satext (<0.9,>=0.8.0b1)
Requires-Dist: wokkel (<19.0.0,>=18.0.0)
Requires-Dist: omemo (<0.13.0,>=0.11.0)
Requires-Dist: omemo-backend-signal (<0.3)
Requires-Dist: pyyaml (<5.5.0)
Provides-Extra: svg
Requires-Dist: CairoSVG ; extra == 'svg'
